{
  "offset": 0,
  "results": [
    {
      "image": "http://rumahdijual.org/athumb/e/8/b/2277553.jpg",
      "km": "4",
      "agent": "Yafet Sutanto",
      "image/_title": "RumahDijual: Rumah Pondok Indah Dekat PIM 2 - Belakang SD/SMP Bakti Mulya 400",
      "lt": "257 m 2 tanah",
      "hp": "081718 ...",
      "description": "(Pinang Perak) Jl Pinang Perak no.5 Jakarta Selatan, 257 m 2",
      "kt": "4",
      "date2": "17 Februari 2015",
      "image/_alt": "Gambar Rumah Pondok Indah Dekat PIM 2 - Belakang SD/SMP Bakti Mulya 400",
      "title": "Rumah Pondok Indah Dekat PIM 2 - Belakang SD/SMP Bakti Mulya 400",
      "price": "10.5 miliar",
      "lb": "350 m 2 bangunan",
      "region": "Pondok Indah"
    },
    {
      "image": "http://rumahdijual.org/athumb/4/5/a/2277315.jpg",
      "km": "4",
      "agent": "Rizki Darmawan",
      "image/_title": "RumahDijual: Rumah Asri dan Bersih PONDOK INDAH",
      "lt": "302 m 2 tanah",
      "hp": "081297 ...",
      "description": "(Jl.ALAM SEGAR) Jl.Alam Segar Pondok Indah Jakarta Selatan, 302 m 2",
      "kt": "4",
      "date2": "17 Februari 2015",
      "image/_alt": "Gambar Rumah Asri dan Bersih PONDOK INDAH",
      "title": "Rumah Asri dan Bersih PONDOK INDAH",
      "price": "13.9 miliar",
      "lb": "450 m 2 bangunan",
      "region": "Pondok Indah"
    },
    {
      "image": "http://rumahdijual.org/athumb/0/f/3/2277197.jpg",
      "km": "4",
      "agent": "Depi Permana",
      "image/_title": "RumahDijual: Rumah hook,3 lantai depan taman di mayestik",
      "lt": "225 m 2 tanah",
      "hp": "085715 ...",
      "description": "(Mayestik) MAYESTIK Jakarta Selatan, 225 m 2",
      "kt": "7",
      "date2": "17 Februari 2015",
      "image/_alt": "Gambar Rumah hook,3 lantai depan taman di mayestik",
      "title": "Rumah hook,3 lantai depan taman di mayestik",
      "price": "15 miliar",
      "lb": "550 m 2 bangunan",
      "region": "Kebayoran Baru"
    },
    {
      "image": "http://rumahdijual.org/athumb/3/e/8/2061693.jpg",
      "km": "3",
      "agent": "wida",
      "image/_title": "RumahDijual: Rumah baru siap huni dalam cluster Cilandak",
      "lt": "140 m 2 tanah",
      "hp": "087889 ...",
      "description": "Pondok Labu Jakarta Selatan, 140 m 2",
      "kt": "3",
      "date2": "17 Februari 2015",
      "image/_alt": "Gambar Rumah baru siap huni dalam cluster Cilandak",
      "title": "Rumah baru siap huni dalam cluster Cilandak",
      "price": "3.5 miliar",
      "lb": "185 m 2 bangunan",
      "region": "Pondok Labu"
    },
    {
      "image": "http://rumahdijual.org/athumb/6/b/7/2189739.jpg",
      "km": "3",
      "agent": "wida",
      "image/_title": "RumahDijual: Rumah dijual dalam cluster di Antasari strategis Jakarta Selatan",
      "lt": "130 m 2 tanah",
      "hp": "087889 ...",
      "description": "Antasari Kemang Jakarta Selatan, 130 m 2",
      "kt": "4",
      "date2": "17 Februari 2015",
      "image/_alt": "Gambar Rumah dijual dalam cluster di Antasari strategis Jakarta Selatan",
      "title": "Rumah dijual dalam cluster di Antasari strategis Jakarta Selatan",
      "price": "4.7 miliar",
      "lb": "200 m 2 bangunan",
      "region": "Antasari"
    },
    {
      "image": "http://rumahdijual.org/athumb/a/a/6/2275717.jpg",
      "km": "4",
      "agent": "Muslimin",
      "image/_title": "RumahDijual: Rumah Dengan Tanah Luas di Lebak Bulus, Jaksel",
      "lt": "330 m 2 tanah",
      "hp": "081808 ...",
      "description": "Jl. Lebak Lestari, Lebak Bulus, Jakarta Selatan, Jakarta Jakarta Selatan, 330 m 2",
      "kt": "4",
      "date2": "17 Februari 2015",
      "image/_alt": "Gambar Rumah Dengan Tanah Luas di Lebak Bulus, Jaksel",
      "title": "Rumah Dengan Tanah Luas di Lebak Bulus, Jaksel",
      "price": "17 miliar",
      "lb": "350 m 2 bangunan",
      "region": "Lebak Bulus"
    },
    {
      "image": "http://rumahdijual.org/athumb/4/8/3/1970826.jpg",
      "km": "3",
      "agent": "Rizki Pro",
      "image/_title": "RumahDijual: Rumah baru minimalis di kemang dalam",
      "lt": "140 m 2 tanah",
      "hp": "081195 ...",
      "description": "(kemang Dalam) jl.kemang Dalam,kemang Jakarta Selatan -- Kemang, 140 m 2",
      "kt": "4",
      "date2": "17 Februari 2015",
      "image/_alt": "Gambar Rumah baru minimalis di kemang dalam",
      "title": "Rumah baru minimalis di kemang dalam",
      "price": "5.6 miliar",
      "lb": "210 m 2 bangunan",
      "region": "Kemang"
    },
    {
      "image": "http://rumahdijual.org/athumb/d/c/3/2275380.jpg",
      "km": "2",
      "agent": "Norick Indradjit",
      "image/_title": "RumahDijual: Jalan Cililin, Kebayoran Baru Dijual Mahal",
      "lt": "190 m 2 tanah",
      "hp": [
        "Lihat peta lokasi",
        "081180 ..."
      ],
      "description": "Jalan Cililin III, Petogogan, Kebayoran Baru. Jakarta Selatan, Senopati, PTIK, Tirtayasa, Cikajang Jakarta Selatan, 190 m 2 Lihat peta lokasi",
      "kt": "3",
      "date2": "17 Februari 2015",
      "image/_alt": "Gambar Jalan Cililin, Kebayoran Baru Dijual Mahal",
      "title": "Jalan Cililin, Kebayoran Baru Dijual Mahal",
      "price": "11 miliar",
      "lb": "150 m 2 bangunan",
      "region": "Kebayoran Baru"
    },
    {
      "image": "http://rumahdijual.org/athumb/5/f/0/1139111.jpg",
      "km": "4",
      "agent": "anet harun",
      "image/_title": "RumahDijual: rumah dan kost an",
      "lt": "600 m 2 tanah",
      "hp": "085811 ...",
      "description": "(abdul majid) jl.abdul majid,cipete jakarta selatan Jakarta Selatan, 600 m 2",
      "kt": "7",
      "date2": "17 Februari 2015",
      "image/_alt": "Gambar rumah dan kost an",
      "title": "rumah dan kost an",
      "price": "10 miliar",
      "lb": "250 m 2 bangunan",
      "region": "Cipete"
    },
    {
      "image": "http://rumahdijual.org/athumb/0/c/3/2274660.jpg",
      "km": "4",
      "agent": "Dirman Properti",
      "image/_title": "RumahDijual: Green sarpa residence jaksel",
      "lt": "126 m 2 tanah",
      "hp": [
        "Lihat peta lokasi",
        "081330 ..."
      ],
      "description": "(JL. M KAHFI 1) JL. M KAHFI 1 Jakarta Selatan, 126 m 2 Lihat peta lokasi",
      "kt": "4",
      "date2": "17 Februari 2015",
      "image/_alt": "Gambar Green sarpa residence jaksel",
      "title": "Green sarpa residence jaksel",
      "price": "1.76 miliar",
      "lb": "160 m 2 bangunan",
      "region": "Cilandak"
    },
    {
      "image": "http://rumahdijual.org/athumb/4/7/7/2273657.jpg",
      "km": "3",
      "agent": "Deodatus Prasetyo",
      "image/_title": "RumahDijual: Rumah Fatmawati Cilandak Jakarta Selatan",
      "lt": "600 m 2 tanah",
      "hp": "087870 ...",
      "description": "Cilandak Jakarta Selatan Jakarta Selatan, 600 m 2",
      "kt": "3",
      "date2": "17 Februari 2015",
      "image/_alt": "Gambar Rumah Fatmawati Cilandak Jakarta Selatan",
      "title": "Rumah Fatmawati Cilandak Jakarta Selatan",
      "price": "14 miliar",
      "lb": "350 m 2 bangunan",
      "region": "Cilandak"
    },
    {
      "image": "http://rumahdijual.org/athumb/d/2/4/2273443.jpg",
      "km": "5",
      "agent": "Deodatus Prasetyo",
      "image/_title": "RumahDijual: Rumah Di Cilandak Barat Jakarta Selatan",
      "lt": "240 m 2 tanah",
      "hp": "087870 ...",
      "description": "Cilandak Barat Jakarta Selatan, 240 m 2",
      "kt": "5",
      "date2": "17 Februari 2015",
      "image/_alt": "Gambar Rumah Di Cilandak Barat Jakarta Selatan",
      "title": "Rumah Di Cilandak Barat Jakarta Selatan",
      "price": "5.7 miliar",
      "lb": "180 m 2 bangunan",
      "region": "Cilandak"
    },
    {
      "image": "http://rumahdijual.org/athumb/9/c/2/2273499.jpg",
      "km": "4",
      "agent": "Harcourts Xhome",
      "image/_title": "RumahDijual: Rumah Bagus, Siap Huni di Pinang Pondok Indah",
      "lt": "200 m 2 tanah",
      "hp": "087881 ...",
      "description": "Pinang Pondok Indah Jakarta Selatan, 200 m 2",
      "kt": "4",
      "date2": "17 Februari 2015",
      "image/_alt": "Gambar Rumah Bagus, Siap Huni di Pinang Pondok Indah",
      "title": "Rumah Bagus, Siap Huni di Pinang Pondok Indah",
      "price": "10 miliar",
      "lb": "300 m 2 bangunan",
      "region": "Pondok Indah"
    },
    {
      "image": "http://rumahdijual.org/athumb/2/3/9/2273321.jpg",
      "km": "2",
      "agent": "Harcourts Xhome",
      "image/_title": "RumahDijual: Rumah Siap Huni di Pinang Pondok Indah",
      "lt": "153 m 2 tanah",
      "hp": "087881 ...",
      "description": "Pinang Pondok Indah Jakarta Selatan, 153 m 2",
      "kt": "4",
      "date2": "17 Februari 2015",
      "image/_alt": "Gambar Rumah Siap Huni di Pinang Pondok Indah",
      "title": "Rumah Siap Huni di Pinang Pondok Indah",
      "price": "8 miliar",
      "lb": "220 m 2 bangunan",
      "region": "Pondok Indah"
    },
    {
      "image": "http://rumahdijual.org/athumb/3/b/2/2272660.jpg",
      "km": "3",
      "agent": "rendy",
      "image/_title": "RumahDijual: Rumah Tirtayasa",
      "lt": "672 m 2 tanah",
      "hp": "085600 ...",
      "description": "(Tirtayasa) Tirtayasa-Kebayoran Baru Jakarta Selatan, 672 m 2",
      "kt": "4",
      "date2": "17 Februari 2015",
      "image/_alt": "Gambar Rumah Tirtayasa",
      "title": "Rumah Tirtayasa",
      "price": "57 miliar",
      "lb": "510 m 2 bangunan",
      "region": "Kebayoran Baru"
    }
  ],
  "cookies": [
    "bblastvisit=\"1432537415\";Path=\"/\";Domain=\"rumahdijual.com\";Port=\"80\"",
    "bblastactivity=\"0\";Path=\"/\";Domain=\"rumahdijual.com\";Port=\"80\""
  ],
  "connectorVersionGuid": "575f35b0-1b98-4f13-96ab-5740f867cbba",
  "connectorGuid": "85fd9d8f-71ff-4531-a0c3-226790fca313",
  "pageUrl": "http://rumahdijual.com/carirumah.php?transaksi=BELI&jenis=RUMAH&kota=Jakarta+Selatan&q=antasari%2C+ampera%2C+cilandak%2C+cipete%2C+fatmawati%2C+gandaria%2C+kebayoran+baru%2C+kemang%2C+lebak+bulus%2C+panglima+polim%2C+pondok+indah%2C+pondok+labu%2C+pondok+pinang&p=178",
  "outputProperties": [
    {
      "name": "image",
      "type": "IMAGE"
    },
    {
      "name": "title",
      "type": "STRING"
    },
    {
      "name": "description",
      "type": "STRING"
    },
    {
      "name": "price",
      "type": "STRING"
    },
    {
      "name": "lt",
      "type": "STRING"
    },
    {
      "name": "lb",
      "type": "STRING"
    },
    {
      "name": "kt",
      "type": "STRING"
    },
    {
      "name": "km",
      "type": "STRING"
    },
    {
      "name": "region",
      "type": "STRING"
    },
    {
      "name": "agent",
      "type": "STRING"
    },
    {
      "name": "hp",
      "type": "STRING"
    },
    {
      "name": "date2",
      "type": "STRING"
    }
  ]
}
