{
  "offset": 0,
  "results": [
    {
      "image": "http://rumahdijual.org/athumb/0/e/c/2553280.jpg",
      "km": "2",
      "agent": "raja",
      "image/_title": "RumahDijual: rumah cantik,harga murah di kebayoran baru jakarta selatan",
      "lt": "300 m 2 tanah",
      "hp": "+62812 ...",
      "description": "kebayoran baru Jakarta Selatan, 300 m 2",
      "kt": "3",
      "date2": "22 April 2015",
      "image/_alt": "Gambar rumah cantik,harga murah di kebayoran baru jakarta selatan",
      "title": "rumah cantik,harga murah di kebayoran baru jakarta selatan",
      "price": "17 miliar",
      "lb": "200 m 2 bangunan",
      "region": "Kebayoran Baru"
    },
    {
      "image": "http://rumahdijual.org/athumb/c/4/5/2524867.jpg",
      "km": "4",
      "agent": "raja",
      "image/_title": "RumahDijual: rumah cantik hoek di pondok indah jakarta selatan",
      "lt": "1600 m 2 tanah",
      "hp": "+62812 ...",
      "description": "pondok indah Jakarta Selatan, 1600 m 2",
      "kt": "5",
      "date2": "22 April 2015",
      "image/_alt": "Gambar rumah cantik hoek di pondok indah jakarta selatan",
      "title": "rumah cantik hoek di pondok indah jakarta selatan",
      "price": "115 miliar",
      "lb": "2000 m 2 bangunan",
      "region": "Pondok Indah"
    },
    {
      "image": "http://rumahdijual.org/athumb/6/e/2/2623856.jpg",
      "km": "4",
      "agent": "Eem",
      "image/_title": "RumahDijual: Rumah murah di Pondok Indah Murah Semi Furnished",
      "lt": "400 m 2 tanah",
      "hp": "081314 ...",
      "description": "(Niaga Hijau) Jl Niaga Hijau 1 Jakarta Selatan, 400 m 2",
      "kt": "4",
      "date2": "22 April 2015",
      "image/_alt": "Gambar Rumah murah di Pondok Indah Murah Semi Furnished",
      "title": "Rumah murah di Pondok Indah Murah Semi Furnished",
      "price": "16.5 miliar",
      "lb": "650 m 2 bangunan",
      "region": "Pondok Indah"
    },
    {
      "image": "http://rumahdijual.org/athumb/c/1/b/1451448.jpg",
      "km": "7",
      "agent": "Tekun Jaya",
      "image/_title": "RumahDijual: Rmh Baru Minimalis LT 333m/LB 380, Pondok Pinang 6.25M nego",
      "lt": "333 m 2 tanah",
      "hp": "085610 ...",
      "description": "(Jalan Nimun Raya) Jalan Nimun Raya, RT 010, Pondok Pinang 12240, Kebayoran Lama Selatan, Kebayoran Lama, Jakarta Selatan Jakarta Selatan, 333 m 2",
      "kt": "6",
      "date2": "22 April 2015",
      "image/_alt": "Gambar Rmh Baru Minimalis LT 333m/LB 380, Pondok Pinang 6.25M nego",
      "title": "Rmh Baru Minimalis LT 333m/LB 380, Pondok Pinang 6.25M nego",
      "price": "6.25 miliar",
      "lb": "380 m 2 bangunan",
      "region": "Pondok Pinang"
    },
    {
      "image": "http://rumahdijual.org/athumb/c/1/1/1162741.jpg",
      "km": "4",
      "agent": "Tekun Jaya",
      "image/_title": "RumahDijual: Rumah Di dekat pondok Indah",
      "lt": "186 m 2 tanah",
      "hp": "085610 ...",
      "description": "(Nimun raya) Seberang Pondok Indah dan Villa Pondok Indah, 150m dari Jalan Ciputat Raya, 5 Menit ke Mal Pondok Indah, Mal Gandaria City, Pintu Tol veteran. Jakarta Selatan, 186 m 2",
      "kt": "3",
      "date2": "22 April 2015",
      "image/_alt": "Gambar Rumah Di dekat pondok Indah",
      "title": "Rumah Di dekat pondok Indah",
      "price": "3.45 miliar",
      "lb": "200 m 2 bangunan",
      "region": "Pondok Pinang"
    },
    {
      "image": "http://rumahdijual.org/athumb/c/8/3/2383116.jpg",
      "km": "2",
      "agent": "Bimo Gumelar",
      "image/_title": "RumahDijual: Rumah Panglima Polim Raya, Jakarta Selatan",
      "lt": "300 m 2 tanah",
      "hp": "089999 ...",
      "description": "(Jl. Panglima Polim Raya) Jl. Panglima Polim, Kebayoran Baru, Jakarta Selatan Jakarta Selatan, 300 m 2",
      "kt": "4",
      "date2": "22 April 2015",
      "image/_alt": "Gambar Rumah Panglima Polim Raya, Jakarta Selatan",
      "title": "Rumah Panglima Polim Raya, Jakarta Selatan",
      "price": "6.7 miliar",
      "lb": "280 m 2 bangunan",
      "region": "Kebayoran Baru"
    },
    {
      "image": "http://rumahdijual.org/athumb/7/3/3/2383055.jpg",
      "km": "2",
      "agent": "Bimo Gumelar",
      "image/_title": "RumahDijual: Rumah Siap Huni Jakarta Selatan",
      "lt": "90 m 2 tanah",
      "hp": "089999 ...",
      "description": "Radio Dalam, Kebayoran Baru, Jakarta Selatan Jakarta Selatan, 90 m 2",
      "kt": "4",
      "date2": "22 April 2015",
      "image/_alt": "Gambar Rumah Siap Huni Jakarta Selatan",
      "title": "Rumah Siap Huni Jakarta Selatan",
      "price": "1.5 miliar",
      "lb": "160 m 2 bangunan",
      "region": "Radio Dalam"
    },
    {
      "image": "http://rumahdijual.org/athumb/d/4/9/2478366.jpg",
      "km": "4",
      "agent": "Hadis jasajakarta.com",
      "image/_title": "RumahDijual: Jual Townhouse Modern di cilandak Tengah jakarta Selatan",
      "lt": "134 m 2 tanah",
      "hp": [
        "Lihat peta lokasi",
        "081566 ..."
      ],
      "description": "(akhyati townhouse jl berkah 1 cilndak jakarta selatan) akhyati townhouse jl al barkah 1 cilandak jakarta selatan Jakarta Selatan (kredit: bisa KPR), 134 m 2 Lihat peta lokasi",
      "kt": "4",
      "date2": "22 April 2015",
      "image/_alt": "Gambar Jual Townhouse Modern di cilandak Tengah jakarta Selatan",
      "title": "Jual Townhouse Modern di cilandak Tengah jakarta Selatan",
      "price": "6.3 miliar",
      "lb": "308 m 2 bangunan",
      "region": "Cilandak"
    },
    {
      "image": "http://rumahdijual.org/athumb/e/3/7/2623169.jpg",
      "km": "4",
      "agent": "tjhin ling erl",
      "image/_title": "RumahDijual: River valley residence",
      "lt": "144 m 2 tanah",
      "hp": "081768 ...",
      "description": "Jl. Lebak Bulus PDK JAKARTA SELATAN Jakarta Selatan, 144 m 2",
      "kt": "4",
      "date2": "22 April 2015",
      "image/_alt": "Gambar River valley residence",
      "title": "River valley residence",
      "price": "5 miliar",
      "lb": "256 m 2 bangunan",
      "region": "Fatmawati"
    },
    {
      "image": "http://rumahdijual.org/athumb/4/2/2/1408578.jpg",
      "km": "4",
      "agent": "Michael Setiadi",
      "image/_title": "RumahDijual: Dijual rumah baru dekat pondok indah mall",
      "lt": "159 m 2 tanah",
      "hp": "081908 ...",
      "description": "PONDOK INDAH Jakarta Selatan, 159 m 2",
      "kt": "4",
      "date2": "22 April 2015",
      "image/_alt": "Gambar Dijual rumah baru dekat pondok indah mall",
      "title": "Dijual rumah baru dekat pondok indah mall",
      "price": "8 miliar",
      "lb": "220 m 2 bangunan",
      "region": "Pondok Indah"
    },
    {
      "image": "http://rumahdijual.org/athumb/6/d/3/2622641.jpg",
      "km": "3",
      "agent": "Dafi",
      "image/_title": "RumahDijual: Rumah baru dijual murah pondok indah",
      "lt": "121 m 2 tanah",
      "hp": "087784 ...",
      "description": "Pondok Indah Jakarta Selatan Jakarta Selatan, 121 m 2",
      "kt": "3",
      "date2": "22 April 2015",
      "image/_alt": "Gambar Rumah baru dijual murah pondok indah",
      "title": "Rumah baru dijual murah pondok indah",
      "price": "7.3 miliar",
      "lb": "250 m 2 bangunan",
      "region": "Pondok Indah"
    },
    {
      "image": "http://rumahdijual.org/athumb/0/0/1/2229957.jpg",
      "km": "3",
      "agent": "Erlangga Rizaldy",
      "image/_title": "RumahDijual: Rumah dijual di Gandaria",
      "lt": "156 m 2 tanah",
      "hp": "087781 ...",
      "description": "Gandaria, Jakarta Selatan Jakarta Selatan, 156 m 2",
      "kt": "4",
      "date2": "22 April 2015",
      "image/_alt": "Gambar Rumah dijual di Gandaria",
      "title": "Rumah dijual di Gandaria",
      "price": "4.5 miliar",
      "lb": "240 m 2 bangunan",
      "region": "Gandaria"
    },
    {
      "image": "http://rumahdijual.org/athumb/3/3/d/2192986.jpg",
      "agent": "Jay Said",
      "image/_title": "RumahDijual: Jarang Ada Tanah 1.700 M2 Cuma 20 Meter Ke Fatmawati Raya",
      "lt": "1700 m 2 tanah",
      "hp": "081288 ...",
      "description": "(jalan Maritim (seberang Subud Fatmawati)) jalan Maritim (seberang Subud Fatmawati) jakarta Selatan, 1700 m 2",
      "kt": "10",
      "date2": "22 April 2015",
      "image/_alt": "Gambar Jarang Ada Tanah 1.700 M2 Cuma 20 Meter Ke Fatmawati Raya",
      "title": "Jarang Ada Tanah 1.700 M2 Cuma 20 Meter Ke Fatmawati Raya",
      "price": "25 juta",
      "lb": "600 m 2 bangunan",
      "region": "Cilandak"
    },
    {
      "image": "http://rumahdijual.org/athumb/2/0/f/2622084.jpg",
      "km": "2",
      "agent": "R. Rizal",
      "image/_title": "RumahDijual: Rumah Baru Siap Huni Dalam Cluster Di Lebak Bulus Jakarta Selatan",
      "lt": "142 m 2 tanah",
      "hp": [
        "Lihat peta lokasi",
        "081380 ..."
      ],
      "description": "Adyaksa, Lebak Bulus Jakarta Selatan, 142 m 2 Lihat peta lokasi",
      "kt": "3",
      "date2": "22 April 2015",
      "image/_alt": "Gambar Rumah Baru Siap Huni Dalam Cluster Di Lebak Bulus Jakarta Selatan",
      "title": "Rumah Baru Siap Huni Dalam Cluster Di Lebak Bulus Jakarta Selatan",
      "price": "4.1 miliar",
      "lb": "132 m 2 bangunan",
      "region": "Lebak Bulus"
    },
    {
      "image": "http://rumahdijual.org/athumb/1/d/3/2621857.jpg",
      "km": "3",
      "agent": "Ristiawan LJ Hooker Cinere",
      "image/_title": "RumahDijual: Rumah brand new @ Cilandak CITOS",
      "lt": "158 m 2 tanah",
      "hp": "082114 ...",
      "description": "Cilandak Jakarta Selatan, 158 m 2",
      "kt": "3",
      "date2": "22 April 2015",
      "image/_alt": "Gambar Rumah brand new @ Cilandak CITOS",
      "title": "Rumah brand new @ Cilandak CITOS",
      "price": "6.5 miliar",
      "lb": "220 m 2 bangunan",
      "region": "Cilandak"
    }
  ],
  "cookies": [
    "bblastvisit=\"1432537357\";Path=\"/\";Domain=\"rumahdijual.com\";Port=\"80\"",
    "bblastactivity=\"0\";Path=\"/\";Domain=\"rumahdijual.com\";Port=\"80\""
  ],
  "connectorVersionGuid": "575f35b0-1b98-4f13-96ab-5740f867cbba",
  "connectorGuid": "85fd9d8f-71ff-4531-a0c3-226790fca313",
  "pageUrl": "http://rumahdijual.com/carirumah.php?transaksi=BELI&jenis=RUMAH&kota=Jakarta+Selatan&q=antasari%2C+ampera%2C+cilandak%2C+cipete%2C+fatmawati%2C+gandaria%2C+kebayoran+baru%2C+kemang%2C+lebak+bulus%2C+panglima+polim%2C+pondok+indah%2C+pondok+labu%2C+pondok+pinang&p=120",
  "outputProperties": [
    {
      "name": "image",
      "type": "IMAGE"
    },
    {
      "name": "title",
      "type": "STRING"
    },
    {
      "name": "description",
      "type": "STRING"
    },
    {
      "name": "price",
      "type": "STRING"
    },
    {
      "name": "lt",
      "type": "STRING"
    },
    {
      "name": "lb",
      "type": "STRING"
    },
    {
      "name": "kt",
      "type": "STRING"
    },
    {
      "name": "km",
      "type": "STRING"
    },
    {
      "name": "region",
      "type": "STRING"
    },
    {
      "name": "agent",
      "type": "STRING"
    },
    {
      "name": "hp",
      "type": "STRING"
    },
    {
      "name": "date2",
      "type": "STRING"
    }
  ]
}
