{
  "offset": 0,
  "results": [
    {
      "image": "http://rumahdijual.org/athumb/a/5/6/2238569.jpg",
      "km": "4",
      "agent": "ismatullah chikal",
      "image/_title": "RumahDijual: Di jual rumah berikut rumah kost,di kawasan lebak bulus",
      "lt": "212 m 2 tanah",
      "hp": "081380 ...",
      "description": "(jalan Komplek Pu Jakarta Selatan) jalan Lebak Bulus Jakarta Selatan jakarta Selatan, 212 m 2",
      "kt": "10",
      "date2": "10 Februari 2015",
      "image/_alt": "Gambar Di jual rumah berikut rumah kost,di kawasan lebak bulus",
      "title": "Di jual rumah berikut rumah kost,di kawasan lebak bulus",
      "price": "4.5 miliar",
      "lb": "400 m 2 bangunan",
      "region": "Lebak Bulus"
    },
    {
      "image": "http://rumahdijual.org/athumb/b/f/7/2237357.jpg",
      "agent": "Jual Atau Cari Property CallMe",
      "price": "10 juta",
      "image/_title": "RumahDijual: Rumah butuh uang biaya rumah sakit bebas banjir 100%",
      "lt": "240 m 2 tanah",
      "hp": "081297 ...",
      "description": "(Gandaria Selatan) Fatmawati Gandaria Selatan Cilandak Jakarta Selatan Jual hitung tanah, 240 m 2",
      "date2": "10 Februari 2015",
      "image/_alt": "Gambar Rumah butuh uang biaya rumah sakit bebas banjir 100%",
      "title": "Rumah butuh uang biaya rumah sakit bebas banjir 100%",
      "region": "Fatmawati"
    },
    {
      "image": "http://rumahdijual.org/athumb/4/b/3/2236646.jpg",
      "km": "17",
      "agent": "dicky martino",
      "image/_title": "RumahDijual: Dijual Rumah di Pondok Labu, startegis untuk usaha",
      "lt": "267 m 2 tanah",
      "hp": "081197 ...",
      "description": "(Jalan Pondok Labu IA) Jalan Pondok Labu IA No. 32 Rt. 008/007 Pondok Labu, Cilandak, Jakarta Selatan 12450 Jakarta Selatan, 267 m 2",
      "kt": "17",
      "date2": "10 Februari 2015",
      "image/_alt": "Gambar Dijual Rumah di Pondok Labu, startegis untuk usaha",
      "title": "Dijual Rumah di Pondok Labu, startegis untuk usaha",
      "price": "3 miliar",
      "lb": "17 17",
      "region": "Pondok Labu"
    },
    {
      "image": "http://rumahdijual.org/athumb/f/b/d/2236627.jpg",
      "km": "3",
      "agent": "fia hidayat",
      "image/_title": "RumahDijual: Alam asri pondok indah rumah lama.harga murah...",
      "lt": "268 m 2 tanah",
      "hp": "081384 ...",
      "description": "(jl.alam asri pondok indah) Jl.alam asri pondok indah Jakarta Selatan, 268 m 2",
      "kt": "4",
      "date2": "10 Februari 2015",
      "image/_alt": "Gambar Alam asri pondok indah rumah lama.harga murah...",
      "title": "Alam asri pondok indah rumah lama.harga murah...",
      "price": "10.6 miliar",
      "lb": "300 m 2 bangunan",
      "region": "Pondok Indah"
    },
    {
      "image": "http://rumahdijual.org/athumb/9/a/2/2236559.jpg",
      "km": "3",
      "agent": "fia hidayat",
      "image/_title": "RumahDijual: Alam asri pondok indah...siap huni..",
      "lt": "262 m 2 tanah",
      "hp": "081384 ...",
      "description": "(alam asri) Alam asri pondok indah Jakarta Selatan, 262 m 2",
      "kt": "4",
      "date2": "10 Februari 2015",
      "image/_alt": "Gambar Alam asri pondok indah...siap huni..",
      "title": "Alam asri pondok indah...siap huni..",
      "price": "12 miliar",
      "lb": "350 m 2 bangunan",
      "region": "Pondok Indah"
    },
    {
      "image": "http://rumahdijual.org/athumb/9/f/5/1765462.jpg",
      "km": "2",
      "agent": "Roy Steven",
      "image/_title": "RumahDijual: Rumah Di Daerah Tenang  Elite Jakarta Selatan",
      "lt": "720 m 2 tanah",
      "hp": [
        "Lihat peta lokasi",
        "081115 ..."
      ],
      "description": "(Wijaya Kusuma) Jl. Wijaya Kusuma Raya No.4 Kebayoran Baru Jakarta Selatan Jakarta Selatan, 720 m 2 Lihat peta lokasi",
      "kt": "4",
      "date2": "10 Februari 2015",
      "image/_alt": "Gambar Rumah Di Daerah Tenang  Elite Jakarta Selatan",
      "title": "Rumah Di Daerah Tenang Elite Jakarta Selatan",
      "price": "12 miliar",
      "lb": "300 m 2 bangunan",
      "region": "Kebayoran Baru"
    },
    {
      "image": "http://rumahdijual.org/athumb/3/9/0/2131744.jpg",
      "km": "6",
      "agent": "Roy Steven",
      "image/_title": "RumahDijual: Rumah Daerah Super Elite Pondok Indah",
      "lt": "822 m 2 tanah",
      "hp": "081115 ...",
      "description": "Alam Asri-Pondok Indah Jakarta Selatan Jakarta Selatan, 822 m 2",
      "kt": "6",
      "date2": "10 Februari 2015",
      "image/_alt": "Gambar Rumah Daerah Super Elite Pondok Indah",
      "title": "Rumah Daerah Super Elite Pondok Indah",
      "price": "43 miliar",
      "lb": "545 m 2 bangunan",
      "region": "Pondok Indah"
    },
    {
      "image": "http://rumahdijual.org/athumb/b/7/3/2080604.jpg",
      "km": "5",
      "agent": "Kurniawan / 2B2432B1",
      "image/_title": "RumahDijual: Rumah Mewah di Kemang dengan Design Modern + Kolam Renang",
      "lt": "612 m 2 tanah",
      "hp": "081806 ...",
      "description": "jl. Bangka XI Kemang, Jakarta Selatan -- Kemang, 612 m 2",
      "kt": "5",
      "date2": "10 Februari 2015",
      "image/_alt": "Gambar Rumah Mewah di Kemang dengan Design Modern + Kolam Renang",
      "title": "Rumah Mewah di Kemang dengan Design Modern + Kolam Renang",
      "price": "21 miliar",
      "lb": "525 m 2 bangunan",
      "region": "Bangka"
    },
    {
      "image": "http://rumahdijual.org/athumb/5/5/9/2236289.jpg",
      "km": "4",
      "agent": "Steven H",
      "image/_title": "RumahDijual: Rumah Adhyaksa  Raya - Lebak bulus",
      "lt": "505 m 2 tanah",
      "hp": [
        "Lihat peta lokasi",
        "081876 ..."
      ],
      "description": "(Adhyaksa Raya) Jalan Adhyaksa Raya Kav P 25, Lebak Bulus, Jakarta Selatan ( 200 meter belakang hotel Mercure) Jakarta Selatan, 505 m 2 Lihat peta lokasi",
      "kt": "5",
      "date2": "10 Februari 2015",
      "image/_alt": "Gambar Rumah Adhyaksa  Raya - Lebak bulus",
      "title": "Rumah Adhyaksa Raya - Lebak bulus",
      "price": "11.5 miliar",
      "lb": "400 m 2 bangunan",
      "region": "Lebak Bulus"
    },
    {
      "image": "http://rumahdijual.org/athumb/3/5/4/2235396.jpg",
      "km": "2",
      "agent": "Grace",
      "image/_title": "RumahDijual: rumah di Fatmawati, Jakarta Selatan",
      "lt": "201 m 2 tanah",
      "hp": "0812...",
      "description": "Jl. Wahyu. Fatmawati, Jakarta Selatan Jakarta Selatan, 201 m 2",
      "kt": "3",
      "date2": "9 Februari 2015",
      "image/_alt": "Gambar rumah di Fatmawati, Jakarta Selatan",
      "title": "rumah di Fatmawati, Jakarta Selatan",
      "price": "5 miliar",
      "lb": "300 m 2 bangunan",
      "region": "Fatmawati"
    },
    {
      "image": "http://rumahdijual.org/athumb/0/6/9/2235068.jpg",
      "km": "5",
      "agent": "Syafrizul Hendra",
      "image/_title": "RumahDijual: Dijual Cepat Rumah Mewah di Pondok Indah",
      "lt": "422 m 2 tanah",
      "hp": "087715 ...",
      "description": "9 Februari 2015",
      "kt": "5",
      "image/_alt": "Gambar Dijual Cepat Rumah Mewah di Pondok Indah",
      "title": "Dijual Cepat Rumah Mewah di Pondok Indah",
      "price": "20 miliar",
      "lb": "400 m 2 bangunan",
      "region": "Pondok Indah"
    },
    {
      "image": "http://rumahdijual.org/athumb/7/8/d/1534054.jpg",
      "km": "2",
      "agent": "Dewo Asmoro",
      "image/_title": "RumahDijual: Rumah Dijual Di Kebayoran Baru",
      "lt": "210 m 2 tanah",
      "hp": [
        "Lihat peta lokasi",
        "081777 ..."
      ],
      "description": "Jl. Jembatan Timur Kebayoran Baru Jakarta Selatan, 210 m 2 Lihat peta lokasi",
      "kt": "5",
      "date2": "9 Februari 2015",
      "image/_alt": "Gambar Rumah Dijual Di Kebayoran Baru",
      "title": "Rumah Dijual Di Kebayoran Baru",
      "price": "6.9 miliar",
      "lb": "185 m 2 bangunan",
      "region": "Kebayoran Baru"
    },
    {
      "image": "http://rumahdijual.org/athumb/3/1/2/2234800.jpg",
      "km": "1",
      "agent": "Winny Otto",
      "image/_title": "RumahDijual: Rumah Siap Huni,strategis di Kemang Utara",
      "lt": "368 m 2 tanah",
      "hp": "085610 ...",
      "description": "Kemang Utara Jakarta Selatan, 368 m 2",
      "kt": "3",
      "date2": "9 Februari 2015",
      "image/_alt": "Gambar Rumah Siap Huni,strategis di Kemang Utara",
      "title": "Rumah Siap Huni,strategis di Kemang Utara",
      "price": "6.5 miliar",
      "lb": "168 m 2 bangunan",
      "region": "Kemang"
    },
    {
      "image": "http://rumahdijual.org/athumb/d/d/b/2233628.jpg",
      "km": "3",
      "agent": "dea",
      "image/_title": "RumahDijual: lokasi strategis jalan kerinci",
      "lt": "315 m 2 tanah",
      "hp": "081288 ...",
      "description": "(jalan kerinci mayestik) jalan kerinci mayestik Jakarta Selatan, 315 m 2",
      "kt": "3",
      "date2": "9 Februari 2015",
      "image/_alt": "Gambar lokasi strategis jalan kerinci",
      "title": "lokasi strategis jalan kerinci",
      "price": "25 miliar",
      "lb": "315 m 2 bangunan",
      "region": "Kebayoran Baru"
    },
    {
      "image": "http://rumahdijual.org/athumb/2/3/2/2232472.jpg",
      "km": "3",
      "agent": "Hen hen",
      "image/_title": "RumahDijual: Pondok indah rumah 580 m2 di sekolah duta dijual cepat (ngantong)",
      "lt": "580 m 2 tanah",
      "hp": "085881 ...",
      "description": "(sekolah duta) Sekolah duta Jakarta Selatan, 580 m 2",
      "kt": "4",
      "date2": "9 Februari 2015",
      "image/_alt": "Gambar Pondok indah rumah 580 m2 di sekolah duta dijual cepat (ngantong)",
      "title": "Pondok indah rumah 580 m2 di sekolah duta dijual cepat (ngantong)",
      "price": "27 miliar",
      "lb": "365 m 2 bangunan",
      "region": "Pondok Indah"
    }
  ],
  "cookies": [
    "bblastvisit=\"1432537420\";Path=\"/\";Domain=\"rumahdijual.com\";Port=\"80\"",
    "bblastactivity=\"0\";Path=\"/\";Domain=\"rumahdijual.com\";Port=\"80\""
  ],
  "connectorVersionGuid": "575f35b0-1b98-4f13-96ab-5740f867cbba",
  "connectorGuid": "85fd9d8f-71ff-4531-a0c3-226790fca313",
  "pageUrl": "http://rumahdijual.com/carirumah.php?transaksi=BELI&jenis=RUMAH&kota=Jakarta+Selatan&q=antasari%2C+ampera%2C+cilandak%2C+cipete%2C+fatmawati%2C+gandaria%2C+kebayoran+baru%2C+kemang%2C+lebak+bulus%2C+panglima+polim%2C+pondok+indah%2C+pondok+labu%2C+pondok+pinang&p=183",
  "outputProperties": [
    {
      "name": "image",
      "type": "IMAGE"
    },
    {
      "name": "title",
      "type": "STRING"
    },
    {
      "name": "description",
      "type": "STRING"
    },
    {
      "name": "price",
      "type": "STRING"
    },
    {
      "name": "lt",
      "type": "STRING"
    },
    {
      "name": "lb",
      "type": "STRING"
    },
    {
      "name": "kt",
      "type": "STRING"
    },
    {
      "name": "km",
      "type": "STRING"
    },
    {
      "name": "region",
      "type": "STRING"
    },
    {
      "name": "agent",
      "type": "STRING"
    },
    {
      "name": "hp",
      "type": "STRING"
    },
    {
      "name": "date2",
      "type": "STRING"
    }
  ]
}
