{
  "offset": 0,
  "results": [
    {
      "image": "http://rumahdijual.org/athumb/4/4/0/2569272.jpg",
      "km": "4",
      "agent": "Ristiawan LJ Hooker Cinere",
      "image/_title": "RumahDijual: Rumah Siap Huni @Cipete",
      "lt": "450 m 2 tanah",
      "hp": "082114 ...",
      "description": "Cipete Jakarta Selatan Jakarta Selatan, 450 m 2",
      "kt": "6",
      "date2": "13 April 2015",
      "image/_alt": "Gambar Rumah Siap Huni @Cipete",
      "title": "Rumah Siap Huni @Cipete",
      "price": "15 miliar",
      "lb": "500 m 2 bangunan",
      "region": "Cipete"
    },
    {
      "image": "http://rumahdijual.org/athumb/0/3/f/252157.jpg",
      "km": "5",
      "agent": "Rusdi Bach",
      "image/_title": "RumahDijual: Rumah Lux @ Cipete MPR Gaharu !! Area terbaik Cipete...Elite !!",
      "lt": "1000 m 2 tanah",
      "hp": "081299 ...",
      "description": "Rumah dengan bangunan kokoh dan masih baru...usia bangunan sekitar 2 tahun - 3 tahun, Jadi msh terbilang bangunan baru. Lt = +/ 1000 / Lb = 1200. SHM. 2 Lantai. Lantai marmer dan kusen full kayu jati. Interior mewah. Sudah pasti sangat nyam, 1000 m 2",
      "kt": "4",
      "date2": "13 April 2015",
      "image/_alt": "Gambar Rumah Lux @ Cipete MPR Gaharu !! Area terbaik Cipete...Elite !!",
      "title": "Rumah Lux @ Cipete MPR Gaharu !! Area terbaik Cipete...Elite !!",
      "price": "30 miliar",
      "lb": "1200 m 2 bangunan",
      "region": "Cipete"
    },
    {
      "image": "http://rumahdijual.org/athumb/5/f/1/2230519.jpg",
      "km": "5",
      "agent": "Ismon Febrie",
      "image/_title": "RumahDijual: Dijaual Rumah Jl. Margasatwa  Komplek DDN 2  Pondok Labu",
      "lt": "1033 m 2 tanah",
      "hp": "081293 ...",
      "description": "(Jl Margasatwa Komplek DDN 2) Dijual rumah Jl Margasatwa komplek DDN 2. Pondok Labu Jakarta Selatan, 1033 m 2",
      "kt": "6",
      "date2": "12 April 2015",
      "image/_alt": "Gambar Dijaual Rumah Jl. Margasatwa  Komplek DDN 2  Pondok Labu",
      "title": "Dijaual Rumah Jl. Margasatwa Komplek DDN 2 Pondok Labu",
      "price": "9.8 miliar",
      "lb": "600 m 2 bangunan",
      "region": "Pondok Labu"
    },
    {
      "image": "http://rumahdijual.org/athumb/e/8/3/2566386.jpg",
      "km": "4",
      "agent": "Mitha Nursanty",
      "image/_title": "RumahDijual: Hunian Mewah dan Luas di Anggrek Lestari - Lebak Lestari",
      "lt": "325 m 2 tanah",
      "hp": "081740 ...",
      "description": "(Jl. Anggrek Lestari, Komp Lebak Lestari) Jl. Anggrek Lestari - Komp Lebak Lestari Lebak Bulus Jakarta Selatan Jakarta Selatan, 325 m 2",
      "kt": "4",
      "date2": "12 April 2015",
      "image/_alt": "Gambar Hunian Mewah dan Luas di Anggrek Lestari - Lebak Lestari",
      "title": "Hunian Mewah dan Luas di Anggrek Lestari - Lebak Lestari",
      "price": "13.5 miliar",
      "lb": "500 m 2 bangunan",
      "region": "Lebak Bulus"
    },
    {
      "image": "http://rumahdijual.org/athumb/b/0/6/2566341.jpg",
      "km": "4",
      "agent": "Mitha Nursanty",
      "image/_title": "RumahDijual: Hunian Mewah di Lebak Lestari",
      "lt": "225 m 2 tanah",
      "hp": [
        "Lihat peta lokasi",
        "081740 ..."
      ],
      "description": "(Komplek Lebak Lestari) Kompleks Lebak Lestari Lebak Bulus, Jakarta Selatan Jakarta Selatan, 225 m 2 Lihat peta lokasi",
      "kt": "4",
      "date2": "12 April 2015",
      "image/_alt": "Gambar Hunian Mewah di Lebak Lestari",
      "title": "Hunian Mewah di Lebak Lestari",
      "price": "9.5 miliar",
      "lb": "450 m 2 bangunan",
      "region": "Lebak Bulus"
    },
    {
      "image": "http://rumahdijual.org/athumb/9/2/6/2566130.jpg",
      "km": "4",
      "agent": "fajarajasa",
      "image/_title": "RumahDijual: 1 Rumah area Sentra Bisnis Pondik Pinang, Dijual Cepat.",
      "lt": "180 m 2 tanah",
      "hp": "082298 ...",
      "description": "(Jln. Anggrek H. Muhi Pondok Pinang) Jl. Anggrek H.Muhi. Jakarta Selatan, 180 m 2",
      "kt": "4",
      "date2": "12 April 2015",
      "image/_alt": "Gambar 1 Rumah area Sentra Bisnis Pondik Pinang, Dijual Cepat.",
      "title": "1 Rumah area Sentra Bisnis Pondik Pinang, Dijual Cepat.",
      "price": "2.5 miliar",
      "lb": "120 m 2 bangunan",
      "region": "Pondok Pinang"
    },
    {
      "image": "http://rumahdijual.org/athumb/b/f/2/1540398.jpg",
      "km": "4",
      "agent": "sony",
      "image/_title": "RumahDijual: Dijual kemang timur cluster minimalis modern new pool lux!!",
      "lt": "240 m 2 tanah",
      "hp": [
        "Lihat peta lokasi",
        "087881 ..."
      ],
      "description": "(jl Kemang Timur) jl Kemang Timur Jakarta Selatan -- Kemang, 240 m 2 Lihat peta lokasi",
      "kt": "4",
      "date2": "12 April 2015",
      "image/_alt": "Gambar Dijual kemang timur cluster minimalis modern new pool lux!!",
      "title": "Dijual kemang timur cluster minimalis modern new pool lux!!",
      "price": "10 miliar",
      "lb": "400 m 2 bangunan",
      "region": "Kemang"
    },
    {
      "image": "http://rumahdijual.org/athumb/4/2/6/1853760.jpg",
      "km": "4",
      "agent": "Trans Property",
      "image/_title": "RumahDijual: Dijual cepat rumah brand new pondok indah",
      "lt": "254 m 2 tanah",
      "hp": "087...",
      "description": "(Jl kartika pinang) Jakarta selatan Jakarta Selatan (kredit: bisa KPR), 254 m 2",
      "kt": "5",
      "date2": "12 April 2015",
      "image/_alt": "Gambar Dijual cepat rumah brand new pondok indah",
      "title": "Dijual cepat rumah brand new pondok indah",
      "price": "18 miliar",
      "lb": "300 m 2 bangunan",
      "region": "Pondok Indah"
    },
    {
      "image": "http://rumahdijual.org/athumb/c/1/0/1800363.jpg",
      "km": "3",
      "agent": "Dafi",
      "image/_title": "RumahDijual: Rumah Klasik murah Pondok Indah",
      "lt": "290 m 2 tanah",
      "hp": "087784 ...",
      "description": "Pondok Indah Jakarta Selatan Jakarta Selatan, 290 m 2",
      "kt": "4",
      "date2": "12 April 2015",
      "image/_alt": "Gambar Rumah Klasik murah Pondok Indah",
      "title": "Rumah Klasik murah Pondok Indah",
      "price": "18 miliar",
      "lb": "354 m 2 bangunan",
      "region": "Pondok Indah"
    },
    {
      "image": "http://rumahdijual.org/athumb/2/f/8/674163.jpg",
      "km": "3",
      "agent": "Binadika 085718258817",
      "image/_title": "RumahDijual: Jual Rumah Mewah Rp 3.5 M di jagakarsa",
      "lt": "800 m 2 tanah",
      "hp": "085718 ...",
      "description": "Jl. Gandaria Ujung Jagakarsa Jakarta Selatan Jakarta Selatan, 800 m 2",
      "kt": "4",
      "date2": "12 April 2015",
      "image/_alt": "Gambar Jual Rumah Mewah Rp 3.5 M di jagakarsa",
      "title": "Jual Rumah Mewah Rp 3.5 M di jagakarsa",
      "price": "3.5 miliar",
      "lb": "300 m 2 bangunan",
      "region": "Jagakarsa"
    },
    {
      "image": "http://rumahdijual.org/athumb/e/4/4/1099650.jpg",
      "km": "1",
      "agent": "Chandra Hidayat",
      "image/_title": "RumahDijual: Rumah layak huni",
      "lt": "30 m 2 tanah",
      "hp": "021...",
      "description": "(ANDARA) UJUNG Jakarta Selatan, 30 m 2",
      "kt": "1",
      "date2": "12 April 2015",
      "image/_alt": "Gambar Rumah layak huni",
      "title": "Rumah layak huni",
      "price": "95 juta",
      "lb": "25 m 2 bangunan",
      "region": "Pondok Labu"
    },
    {
      "image": "http://rumahdijual.org/athumb/5/2/7/2563885.jpg",
      "km": "5",
      "agent": "Syafrizul Hendra",
      "image/_title": "RumahDijual: Dijual Rumah Mewah di Cipete Selatan, Jakarta Selatan",
      "lt": "1090 m 2 tanah",
      "hp": "087715 ...",
      "description": "Cipete Selatan, Jakarta Selatan Jakarta Selatan, 1090 m 2",
      "kt": "6",
      "date2": "11 April 2015",
      "image/_alt": "Gambar Dijual Rumah Mewah di Cipete Selatan, Jakarta Selatan",
      "title": "Dijual Rumah Mewah di Cipete Selatan, Jakarta Selatan",
      "price": "33 miliar",
      "lb": "800 m 2 bangunan",
      "region": "Cipete"
    },
    {
      "image": "http://rumahdijual.org/athumb/c/3/6/2563204.jpg",
      "km": "3",
      "agent": "Esthie Uthieq",
      "image/_title": "RumahDijual: Rumah di kawasan fatmawati",
      "lt": "700 m 2 tanah",
      "hp": "081299 ...",
      "description": "(JL. FATMAWATI) JL.FATMAWATI JAKARTA SELATAN Jakarta Selatan, 700 m 2",
      "kt": "4",
      "date2": "11 April 2015",
      "image/_alt": "Gambar Rumah di kawasan fatmawati",
      "title": "Rumah di kawasan fatmawati",
      "price": "16.5 miliar",
      "lb": "300 m 2 bangunan",
      "region": "Fatmawati"
    },
    {
      "image": "http://rumahdijual.org/athumb/2/1/3/2563035.jpg",
      "km": "3",
      "agent": "Esthie Uthieq",
      "image/_title": "RumahDijual: Rumah Luas di Kemang Jaksel",
      "lt": "1000 m 2 tanah",
      "hp": "081299 ...",
      "description": "Kemang Jakarta Selatan -- Kemang, 1000 m 2",
      "kt": "4",
      "date2": "11 April 2015",
      "image/_alt": "Gambar Rumah Luas di Kemang Jaksel",
      "title": "Rumah Luas di Kemang Jaksel",
      "price": "27 miliar",
      "lb": "400 m 2 bangunan",
      "region": "Kemang"
    },
    {
      "image": "http://rumahdijual.org/athumb/3/2/1/2562862.jpg",
      "km": "2",
      "agent": "eka pusy mayoka",
      "image/_title": "RumahDijual: Cluster cantik dekat pondok indah 2 lantai",
      "lt": "60 m 2 tanah",
      "hp": "081285 ...",
      "description": "(JL RE MARTHADINATA) CIPUTAT JL RE MARTHADINATA Jakarta Selatan, 60 m 2",
      "kt": "3",
      "date2": "11 April 2015",
      "image/_alt": "Gambar Cluster cantik dekat pondok indah 2 lantai",
      "title": "Cluster cantik dekat pondok indah 2 lantai",
      "price": "600 juta",
      "lb": "60 m 2 bangunan",
      "region": "Ciputat"
    }
  ],
  "cookies": [
    "bblastvisit=\"1432537369\";Path=\"/\";Domain=\"rumahdijual.com\";Port=\"80\"",
    "bblastactivity=\"0\";Path=\"/\";Domain=\"rumahdijual.com\";Port=\"80\""
  ],
  "connectorVersionGuid": "575f35b0-1b98-4f13-96ab-5740f867cbba",
  "connectorGuid": "85fd9d8f-71ff-4531-a0c3-226790fca313",
  "pageUrl": "http://rumahdijual.com/carirumah.php?transaksi=BELI&jenis=RUMAH&kota=Jakarta+Selatan&q=antasari%2C+ampera%2C+cilandak%2C+cipete%2C+fatmawati%2C+gandaria%2C+kebayoran+baru%2C+kemang%2C+lebak+bulus%2C+panglima+polim%2C+pondok+indah%2C+pondok+labu%2C+pondok+pinang&p=132",
  "outputProperties": [
    {
      "name": "image",
      "type": "IMAGE"
    },
    {
      "name": "title",
      "type": "STRING"
    },
    {
      "name": "description",
      "type": "STRING"
    },
    {
      "name": "price",
      "type": "STRING"
    },
    {
      "name": "lt",
      "type": "STRING"
    },
    {
      "name": "lb",
      "type": "STRING"
    },
    {
      "name": "kt",
      "type": "STRING"
    },
    {
      "name": "km",
      "type": "STRING"
    },
    {
      "name": "region",
      "type": "STRING"
    },
    {
      "name": "agent",
      "type": "STRING"
    },
    {
      "name": "hp",
      "type": "STRING"
    },
    {
      "name": "date2",
      "type": "STRING"
    }
  ]
}
